src/__main__.py
src/browser.py
src/downloader.py
src/main.py
src/models.py
src/registry.py
src/ui.py
orca_cli-0.1.0.dist-info/entry_points.txt
orca_cli-0.1.0.dist-info/LICENSE
orca_cli-0.1.0.dist-info/METADATA
orca_cli-0.1.0.dist-info/WHEEL
orca_cli-0.1.0.dist-info/RECORD
